LICENSE
README.md
setup.py
botsacflow/__init__.py
botsacflow/exceptions.py
botsacflow/sacflow.py
botsacflow.egg-info/PKG-INFO
botsacflow.egg-info/SOURCES.txt
botsacflow.egg-info/dependency_links.txt
botsacflow.egg-info/requires.txt
botsacflow.egg-info/top_level.txt